[
  {
    "env": "Xiao_C3_repeater",
    "name": "Seeed XIAO ESP32-C3 Repeater",
    "chipFamily": "ESP32-C3",
    "description": "Small ESP32-C3 repeater build for MeshCoreNG dense-mesh testing."
  },
  {
    "env": "Xiao_S3_WIO_repeater",
    "name": "Seeed XIAO ESP32-S3 WIO Repeater",
    "chipFamily": "ESP32-S3",
    "description": "ESP32-S3 WIO repeater build."
  },
  {
    "env": "Heltec_v3_repeater",
    "name": "Heltec LoRa 32 V3 Repeater",
    "chipFamily": "ESP32-S3",
    "description": "Heltec V3 ESP32-S3 repeater build."
  },
  {
    "env": "heltec_v4_repeater",
    "name": "Heltec LoRa 32 V4 Repeater",
    "chipFamily": "ESP32-S3",
    "description": "Heltec V4 ESP32-S3 repeater build."
  },
  {
    "env": "LilyGo_T3S3_sx1262_repeater",
    "name": "LilyGo T3S3 SX1262 Repeater",
    "chipFamily": "ESP32-S3",
    "description": "LilyGo T3S3 SX1262 repeater build."
  },
  {
    "env": "Tbeam_SX1262_repeater",
    "name": "LilyGo T-Beam SX1262 Repeater",
    "chipFamily": "ESP32",
    "description": "LilyGo T-Beam ESP32 SX1262 repeater build."
  },
  {
    "env": "Station_G2_repeater",
    "name": "Station G2 Repeater",
    "chipFamily": "ESP32-S3",
    "description": "Station G2 ESP32-S3 repeater build."
  }
]
